biocli/__init__.py
biocli/_biocli.py
biocli/count.py
biocli/pattern.py
biocli/translate.py
biocli/_common/__init__.py
biocli/_common/_errors.py
biocli/_common/_helper.py
biocli/_common/_sequence.py
biocli-1.0.1b1.dist-info/entry_points.txt
biocli-1.0.1b1.dist-info/LICENSE.md
biocli-1.0.1b1.dist-info/WHEEL
biocli-1.0.1b1.dist-info/METADATA
biocli-1.0.1b1.dist-info/RECORD
